PyLTI-0.7.0.dist-info/DESCRIPTION.rst
PyLTI-0.7.0.dist-info/METADATA
PyLTI-0.7.0.dist-info/RECORD
PyLTI-0.7.0.dist-info/WHEEL
PyLTI-0.7.0.dist-info/metadata.json
PyLTI-0.7.0.dist-info/top_level.txt
pylti/__init__.py
pylti/chalice.py
pylti/common.py
pylti/flask.py
pylti/tests/__init__.py
pylti/tests/test_chalice.py
pylti/tests/test_chalice_app.py
pylti/tests/test_common.py
pylti/tests/test_flask.py
pylti/tests/test_flask_app.py
pylti/tests/util.py
pylti/tests/data/certs/snakeoil.pem
