Metadata-Version: 1.1
Name: PyLTI
Version: 0.7.0
Summary: PyLTI provides Python Implementation of IMS LTI interface that works with edX
Home-page: http://github.com/mitodl/pylti
Author: MIT ODL Engineering
Author-email: odl-engineering@mit.edu
License: BSD
Platform: UNKNOWN
Classifier: Development Status :: 2 - Pre-Alpha
Classifier: Intended Audience :: Developers
Classifier: Intended Audience :: Education
